miq_version/__init__.py
miq_version/constants.py
miq_version-0.4.1.dist-info/AUTHORS
miq_version-0.4.1.dist-info/COPYING
miq_version-0.4.1.dist-info/METADATA
miq_version-0.4.1.dist-info/WHEEL
miq_version-0.4.1.dist-info/pbr.json
miq_version-0.4.1.dist-info/top_level.txt
miq_version-0.4.1.dist-info/RECORD
