Metadata-Version: 2.1
Name: miq-version
Version: 0.4.1
Summary: A class that ensures correct sorting and parsing of the ManageIQ/CFME version numbers
Home-page: UNKNOWN
Author: Peter Savage
Author-email: psavage@redhat.com
License: Apache
Keywords: setup
Requires-Dist: attrs
Requires-Dist: cached-property
Requires-Dist: deepdiff
Requires-Dist: lxml
Requires-Dist: requests
Requires-Dist: oslo.i18n
Requires-Dist: pytest
